LICENSE
MANIFEST.in
README.md
setup.cfg
setup.py
megaclite/__init__.py
megaclite/megaclite_config.py
megaclite.egg-info/PKG-INFO
megaclite.egg-info/SOURCES.txt
megaclite.egg-info/dependency_links.txt
megaclite.egg-info/requires.txt
megaclite.egg-info/top_level.txt
megaclite/static/index.js
megaclite/static/megaclite.png
megaclite/static/megaclite_350.png