Metadata-Version: 1.0
Name: megaclite
Version: 0.1
Summary: Resource Manager for Jupyter. A moon too.
Home-page: https://github.com/alivcor/megaclite
Author: Abhinandan Dubey
Author-email: abhinandandubey@live.com
License: UNKNOWN
Keywords: jupyterhub,memory,nbextension,jupyter,extension
Platform: UNKNOWN
